oslicensor/__init__.py
oslicensor/__main__.py
oslicensor/commands.py
oslicensor/markdown_converter.py
oslicensor/version.py
oslicensor/assets/agpl.txt
oslicensor/assets/apache.txt
oslicensor/assets/artistic.txt
oslicensor/assets/bsd1.txt
oslicensor/assets/bsd2.txt
oslicensor/assets/bsd3.txt
oslicensor/assets/cc1.txt
oslicensor/assets/cc4.txt
oslicensor/assets/commons-clause.txt
oslicensor/assets/eclipse1.txt
oslicensor/assets/eclipse2.txt
oslicensor/assets/gpl1.txt
oslicensor/assets/gpl2.txt
oslicensor/assets/gpl3.txt
oslicensor/assets/hyppocratic.txt
oslicensor/assets/isc.txt
oslicensor/assets/ldap.txt
oslicensor/assets/lgpl2.txt
oslicensor/assets/lgpl3.txt
oslicensor/assets/mit.txt
oslicensor/assets/mozilla.txt
oslicensor/assets/unlicense.txt
oslicensor/assets/upl.txt
oslicensor/assets/zope.txt
oslicensor-0.1.1.dist-info/LICENSE
oslicensor-0.1.1.dist-info/METADATA
oslicensor-0.1.1.dist-info/WHEEL
oslicensor-0.1.1.dist-info/entry_points.txt
oslicensor-0.1.1.dist-info/top_level.txt
oslicensor-0.1.1.dist-info/RECORD
