Metadata-Version: 2.1
Name: oslicensor
Version: 0.1.1
Summary: OSS License CLI generator.
Home-page: https://github.com/alexpdev/osslicenser
Author: alexpdev
Author-email: alexpdev@protonmail.com
License: Apache License
Keywords: CLI,licenses,oss,developers
Platform: UNKNOWN
License-File: LICENSE
